.gitignore
LICENSE.md
README.md
build_package.py
pyproject.toml
requirements-dev.txt
wpyreg/__init__.py
wpyreg/__main__.py
wpyreg/_key_data_types_generator.py
wpyreg/diff.py
wpyreg/key_data_types.json
wpyreg.egg-info/PKG-INFO
wpyreg.egg-info/SOURCES.txt
wpyreg.egg-info/dependency_links.txt
wpyreg.egg-info/entry_points.txt
wpyreg.egg-info/top_level.txt