Metadata-Version: 2.4
Name: wpyreg
Version: 0.0.0
Summary: python library for handling windows registry with some additional features
Author-email: Wojciech Sobczak <wojcienty@gmail.com>
Maintainer-email: Wojciech Sobczak <wojcienty@gmail.com>
License: ## License
Project-URL: Homepage, https://github.com/WojciechSobczak/wpyreg
Project-URL: Documentation, https://github.com/WojciechSobczak/wpyreg
Project-URL: Repository, https://github.com/WojciechSobczak/wpyreg.git
Project-URL: Issues, https://github.com/WojciechSobczak/wpyreg/issues
Keywords: windows,registry
Requires-Python: >=3.10
License-File: LICENSE.md
Dynamic: license-file
